mofa_stage
