Metadata-Version: 2.4
Name: mofa-stage
Version: 0.5.1
Summary: Web-based development tool for managing and editing Nodes and Dataflows in the MoFA framework
Author-email: MoFA Team <mofa-dev@example.com>
Maintainer-email: MoFA Team <mofa-dev@example.com>
License: MIT
Project-URL: Homepage, https://github.com/mofa-org/mofa-stage
Project-URL: Documentation, https://github.com/mofa-org/mofa-stage#readme
Project-URL: Repository, https://github.com/mofa-org/mofa-stage
Project-URL: Bug Reports, https://github.com/mofa-org/mofa-stage/issues
Keywords: mofa,ai-agent,development-tool,web-ui,stage
Classifier: Development Status :: 3 - Alpha
Classifier: Intended Audience :: Developers
Classifier: License :: OSI Approved :: MIT License
Classifier: Programming Language :: Python :: 3
Classifier: Programming Language :: Python :: 3.8
Classifier: Programming Language :: Python :: 3.9
Classifier: Programming Language :: Python :: 3.10
Classifier: Programming Language :: Python :: 3.11
Classifier: Framework :: Flask
Classifier: Topic :: Software Development :: Libraries :: Application Frameworks
Classifier: Environment :: Web Environment
Requires-Python: >=3.8
Requires-Dist: mofa-ai>=0.2.7
Requires-Dist: click>=8.0.0
Requires-Dist: psutil>=5.9.0
Requires-Dist: flask>=2.3.3
Requires-Dist: flask-cors>=4.0.0
Requires-Dist: pyyaml>=6.0.1
Requires-Dist: toml>=0.10.2
Requires-Dist: python-dotenv>=1.0.0
Requires-Dist: paramiko>=3.3.1
Requires-Dist: flask-sock>=0.6.0
Requires-Dist: webssh>=1.6.2
Requires-Dist: requests>=2.31.0
